<?xml version="1.0"?>
<resource-action-mapping>
	<portlet-resource>
        <portlet-name>politaktiv-map</portlet-name>
        <permissions>
            <supports>
                <action-key>ADD_TO_PAGE</action-key>
                <action-key>CONFIGURATION</action-key>
                <action-key>VIEW</action-key>
                <action-key>EDIT</action-key>
            </supports>
            <site-member-defaults>
                <action-key>VIEW</action-key>
            </site-member-defaults>
            <guest-defaults>
                <action-key>VIEW</action-key>
            </guest-defaults>
            <guest-unsupported>
                <action-key>CONFIGURATION</action-key>
                <action-key>EDIT</action-key>
            </guest-unsupported>
        </permissions>
    </portlet-resource>
     <model-resource>
    	<model-name>org.politaktiv.map.infrastructure.model.Marker</model-name>
    	<portlet-ref>
    		<portlet-name>politaktiv-map</portlet-name>
    	</portlet-ref>
    	
    	<supports>
    		<action-key>VIEW</action-key>
    		<action-key>ADD</action-key>
    		<action-key>UPDATE</action-key>
    		<action-key>DELETE</action-key>
    	</supports>
    	
    	<site-member-defaults>
    		<action-key>VIEW</action-key>
    		<action-key>ADD</action-key>
    		<action-key>UPDATE</action-key>
    		<action-key>DELETE</action-key>
    	</site-member-defaults>
    	
    	<guest-defaults>
    		<action-key>VIEW</action-key>
    	</guest-defaults>
    	<guest-unsupported>
    		<action-key>ADD</action-key>
    		<action-key>UPDATE</action-key>
    		<action-key>DELETE</action-key>
    	</guest-unsupported>
    </model-resource>
    <model-resource>
    	<model-name>org.politaktiv.map.infrastructure.model.Picture</model-name>
    	<portlet-ref>
    		<portlet-name>politaktiv-map</portlet-name>
    	</portlet-ref>
    	<supports>
    		<action-key>VIEW</action-key>
    		<action-key>ADD</action-key>
    		<action-key>UPDATE</action-key>
    		<action-key>DELETE</action-key>
    	</supports>	
    	<site-member-defaults>
    		<action-key>VIEW</action-key>
    		<action-key>ADD</action-key>
    		<action-key>UPDATE</action-key>
    		<action-key>DELETE</action-key>
    	</site-member-defaults>	
    	<guest-defaults>
    		<action-key>VIEW</action-key>
    	</guest-defaults>
    	<guest-unsupported>
    		<action-key>ADD</action-key>
    		<action-key>UPDATE</action-key>
    		<action-key>DELETE</action-key>
    	</guest-unsupported>
    </model-resource>
    
       <model-resource>
    	<model-name>org.politaktiv.map.infrastructure.model.Background</model-name>
    	<portlet-ref>
    		<portlet-name>politaktiv-map</portlet-name>
    	</portlet-ref>
    	<supports>
    		<action-key>VIEW</action-key>
    		<action-key>ADD</action-key>
    		<action-key>UPDATE</action-key>
    		<action-key>DELETE</action-key>
    	</supports>	
    	<site-member-defaults>
    		<action-key>VIEW</action-key>
    	</site-member-defaults>	
    	<guest-defaults>
    		<action-key>VIEW</action-key>
    	</guest-defaults>
    	<guest-unsupported>
    		<action-key>ADD</action-key>
    		<action-key>UPDATE</action-key>
    		<action-key>DELETE</action-key>
    	</guest-unsupported>
    </model-resource>
</resource-action-mapping>